ensureconda/__init__.py
ensureconda/__main__.py
ensureconda/_version.py
ensureconda/api.py
ensureconda/cli.py
ensureconda/installer.py
ensureconda/py.typed
ensureconda/resolve.py
ensureconda-1.6.0.dist-info/METADATA
ensureconda-1.6.0.dist-info/WHEEL
ensureconda-1.6.0.dist-info/entry_points.txt
ensureconda-1.6.0.dist-info/licenses/LICENSE-MIT
ensureconda-1.6.0.dist-info/RECORD
