Metadata-Version: 2.4
Name: ensureconda
Version: 1.6.0
Summary: Lightweight bootstrapper for a conda executable
Project-URL: Homepage, https://github.com/conda-incubator/ensureconda
Author-email: Marius van Niekerk <marius.v.niekerk@gmail.com>
License-Expression: MIT
License-File: LICENSE-MIT
Classifier: Development Status :: 5 - Production/Stable
Classifier: Intended Audience :: Science/Research
Classifier: License :: OSI Approved :: MIT License
Classifier: Operating System :: OS Independent
Classifier: Programming Language :: Python
Classifier: Programming Language :: Python :: 3
Classifier: Programming Language :: Python :: 3.8
Classifier: Programming Language :: Python :: 3.9
Classifier: Programming Language :: Python :: 3.10
Classifier: Programming Language :: Python :: 3.11
Classifier: Programming Language :: Python :: 3.12
Classifier: Programming Language :: Python :: 3.13
Requires-Python: >=3.8
Requires-Dist: appdirs
Requires-Dist: click>=5.1
Requires-Dist: conda-package-streaming
Requires-Dist: filelock
Requires-Dist: packaging
Requires-Dist: requests>=2
Provides-Extra: dev
Requires-Dist: black; extra == 'dev'
Requires-Dist: build; extra == 'dev'
Requires-Dist: coverage; extra == 'dev'
Requires-Dist: docker; extra == 'dev'
Requires-Dist: flake8; extra == 'dev'
Requires-Dist: isort; extra == 'dev'
Requires-Dist: mypy; extra == 'dev'
Requires-Dist: pip; extra == 'dev'
Requires-Dist: pre-commit; extra == 'dev'
Requires-Dist: pytest; extra == 'dev'
Requires-Dist: types-click; extra == 'dev'
Requires-Dist: types-filelock; extra == 'dev'
Requires-Dist: types-requests; extra == 'dev'
